shapeplotter/__init__.py
shapeplotter/shapeplotter.py
shapeplotter-0.3.dist-info/METADATA
shapeplotter-0.3.dist-info/RECORD
shapeplotter-0.3.dist-info/WHEEL
shapeplotter-0.3.dist-info/top_level.txt
