Metadata-Version: 2.1
Name: shapeplotter
Version: 0.3
Summary: A simple library to plot shapely objects.
Home-page: https://github.com/Extintor/shapeplotter
Author: Paul Charbonneau
Author-email: paulcharbo@gmail.com
License: GPLv3
Platform: UNKNOWN
Classifier: Programming Language :: Python :: 3
Classifier: License :: OSI Approved :: GNU General Public License v3 (GPLv3)
Classifier: Operating System :: OS Independent
Classifier: Topic :: Scientific/Engineering :: Visualization
Requires-Dist: matplotlib
